[
  {
    "date": "1996-04",
    "price": 104800
  },
  {
    "date": "1996-05",
    "price": 105700
  },
  {
    "date": "1996-06",
    "price": 106400
  },
  {
    "date": "1996-07",
    "price": 107000
  },
  {
    "date": "1996-08",
    "price": 107500
  },
  {
    "date": "1996-09",
    "price": 108100
  },
  {
    "date": "1996-10",
    "price": 108800
  },
  {
    "date": "1996-11",
    "price": 109500
  },
  {
    "date": "1996-12",
    "price": 110500
  },
  {
    "date": "1997-01",
    "price": 111900
  },
  {
    "date": "1997-02",
    "price": 113300
  },
  {
    "date": "1997-03",
    "price": 114300
  },
  {
    "date": "1997-04",
    "price": 115300
  },
  {
    "date": "1997-05",
    "price": 116200
  },
  {
    "date": "1997-06",
    "price": 117000
  },
  {
    "date": "1997-07",
    "price": 117600
  },
  {
    "date": "1997-08",
    "price": 118200
  },
  {
    "date": "1997-09",
    "price": 118900
  },
  {
    "date": "1997-10",
    "price": 119800
  },
  {
    "date": "1997-11",
    "price": 120700
  },
  {
    "date": "1997-12",
    "price": 122100
  },
  {
    "date": "1998-01",
    "price": 123800
  },
  {
    "date": "1998-02",
    "price": 125400
  },
  {
    "date": "1998-03",
    "price": 126900
  },
  {
    "date": "1998-04",
    "price": 128300
  },
  {
    "date": "1998-05",
    "price": 129500
  },
  {
    "date": "1998-06",
    "price": 130600
  },
  {
    "date": "1998-07",
    "price": 131500
  },
  {
    "date": "1998-08",
    "price": 132500
  },
  {
    "date": "1998-09",
    "price": 133500
  },
  {
    "date": "1998-10",
    "price": 134700
  },
  {
    "date": "1998-11",
    "price": 136100
  },
  {
    "date": "1998-12",
    "price": 137900
  },
  {
    "date": "1999-01",
    "price": 140100
  },
  {
    "date": "1999-02",
    "price": 142300
  },
  {
    "date": "1999-03",
    "price": 144300
  },
  {
    "date": "1999-04",
    "price": 146200
  },
  {
    "date": "1999-05",
    "price": 147800
  },
  {
    "date": "1999-06",
    "price": 149100
  },
  {
    "date": "1999-07",
    "price": 150300
  },
  {
    "date": "1999-08",
    "price": 151400
  },
  {
    "date": "1999-09",
    "price": 152500
  },
  {
    "date": "1999-10",
    "price": 153800
  },
  {
    "date": "1999-11",
    "price": 155200
  },
  {
    "date": "1999-12",
    "price": 157000
  },
  {
    "date": "2000-01",
    "price": 159300
  },
  {
    "date": "2000-02",
    "price": 161700
  },
  {
    "date": "2000-03",
    "price": 163700
  },
  {
    "date": "2000-04",
    "price": 165500
  },
  {
    "date": "2000-05",
    "price": 166900
  },
  {
    "date": "2000-06",
    "price": 168000
  },
  {
    "date": "2000-07",
    "price": 169000
  },
  {
    "date": "2000-08",
    "price": 169800
  },
  {
    "date": "2000-09",
    "price": 170700
  },
  {
    "date": "2000-10",
    "price": 171800
  },
  {
    "date": "2000-11",
    "price": 173100
  },
  {
    "date": "2000-12",
    "price": 174800
  },
  {
    "date": "2001-01",
    "price": 177100
  },
  {
    "date": "2001-02",
    "price": 179600
  },
  {
    "date": "2001-03",
    "price": 181900
  },
  {
    "date": "2001-04",
    "price": 183900
  },
  {
    "date": "2001-05",
    "price": 185500
  },
  {
    "date": "2001-06",
    "price": 186700
  },
  {
    "date": "2001-07",
    "price": 187500
  },
  {
    "date": "2001-08",
    "price": 188200
  },
  {
    "date": "2001-09",
    "price": 189100
  },
  {
    "date": "2001-10",
    "price": 190400
  },
  {
    "date": "2001-11",
    "price": 191900
  },
  {
    "date": "2001-12",
    "price": 193900
  },
  {
    "date": "2002-01",
    "price": 196600
  },
  {
    "date": "2002-02",
    "price": 199700
  },
  {
    "date": "2002-03",
    "price": 202500
  },
  {
    "date": "2002-04",
    "price": 204700
  },
  {
    "date": "2002-05",
    "price": 206300
  },
  {
    "date": "2002-06",
    "price": 207200
  },
  {
    "date": "2002-07",
    "price": 207700
  },
  {
    "date": "2002-08",
    "price": 208000
  },
  {
    "date": "2002-09",
    "price": 208500
  },
  {
    "date": "2002-10",
    "price": 209200
  },
  {
    "date": "2002-11",
    "price": 211400
  },
  {
    "date": "2002-12",
    "price": 214100
  },
  {
    "date": "2003-01",
    "price": 215300
  },
  {
    "date": "2003-02",
    "price": 214600
  },
  {
    "date": "2003-03",
    "price": 213800
  },
  {
    "date": "2003-04",
    "price": 213900
  },
  {
    "date": "2003-05",
    "price": 215400
  },
  {
    "date": "2003-06",
    "price": 218600
  },
  {
    "date": "2003-07",
    "price": 222800
  },
  {
    "date": "2003-08",
    "price": 227500
  },
  {
    "date": "2003-09",
    "price": 231900
  },
  {
    "date": "2003-10",
    "price": 235900
  },
  {
    "date": "2003-11",
    "price": 238900
  },
  {
    "date": "2003-12",
    "price": 240600
  },
  {
    "date": "2004-01",
    "price": 241400
  },
  {
    "date": "2004-02",
    "price": 241500
  },
  {
    "date": "2004-03",
    "price": 241400
  },
  {
    "date": "2004-04",
    "price": 241900
  },
  {
    "date": "2004-05",
    "price": 243400
  },
  {
    "date": "2004-06",
    "price": 245800
  },
  {
    "date": "2004-07",
    "price": 248800
  },
  {
    "date": "2004-08",
    "price": 252000
  },
  {
    "date": "2004-09",
    "price": 255000
  },
  {
    "date": "2004-10",
    "price": 257800
  },
  {
    "date": "2004-11",
    "price": 259000
  },
  {
    "date": "2004-12",
    "price": 258500
  },
  {
    "date": "2005-01",
    "price": 257800
  },
  {
    "date": "2005-02",
    "price": 258900
  },
  {
    "date": "2005-03",
    "price": 262600
  },
  {
    "date": "2005-04",
    "price": 268800
  },
  {
    "date": "2005-05",
    "price": 276500
  },
  {
    "date": "2005-06",
    "price": 285300
  },
  {
    "date": "2005-07",
    "price": 295200
  },
  {
    "date": "2005-08",
    "price": 305700
  },
  {
    "date": "2005-09",
    "price": 316000
  },
  {
    "date": "2005-10",
    "price": 325300
  },
  {
    "date": "2005-11",
    "price": 333800
  },
  {
    "date": "2005-12",
    "price": 342300
  },
  {
    "date": "2006-01",
    "price": 351300
  },
  {
    "date": "2006-02",
    "price": 360500
  },
  {
    "date": "2006-03",
    "price": 369500
  },
  {
    "date": "2006-04",
    "price": 378400
  },
  {
    "date": "2006-05",
    "price": 386700
  },
  {
    "date": "2006-06",
    "price": 394300
  },
  {
    "date": "2006-07",
    "price": 400900
  },
  {
    "date": "2006-08",
    "price": 405900
  },
  {
    "date": "2006-09",
    "price": 410200
  },
  {
    "date": "2006-10",
    "price": 415000
  },
  {
    "date": "2006-11",
    "price": 421100
  },
  {
    "date": "2006-12",
    "price": 428400
  },
  {
    "date": "2007-01",
    "price": 436000
  },
  {
    "date": "2007-02",
    "price": 442700
  },
  {
    "date": "2007-03",
    "price": 447700
  },
  {
    "date": "2007-04",
    "price": 450100
  },
  {
    "date": "2007-05",
    "price": 449800
  },
  {
    "date": "2007-06",
    "price": 447900
  },
  {
    "date": "2007-07",
    "price": 445500
  },
  {
    "date": "2007-08",
    "price": 442800
  },
  {
    "date": "2007-09",
    "price": 440600
  },
  {
    "date": "2007-10",
    "price": 438800
  },
  {
    "date": "2007-11",
    "price": 436900
  },
  {
    "date": "2007-12",
    "price": 434800
  },
  {
    "date": "2008-01",
    "price": 432700
  },
  {
    "date": "2008-02",
    "price": 430200
  },
  {
    "date": "2008-03",
    "price": 427300
  },
  {
    "date": "2008-04",
    "price": 423200
  },
  {
    "date": "2008-05",
    "price": 417700
  },
  {
    "date": "2008-06",
    "price": 411300
  },
  {
    "date": "2008-07",
    "price": 405000
  },
  {
    "date": "2008-08",
    "price": 399200
  },
  {
    "date": "2008-09",
    "price": 394200
  },
  {
    "date": "2008-10",
    "price": 390000
  },
  {
    "date": "2008-11",
    "price": 386400
  },
  {
    "date": "2008-12",
    "price": 383300
  },
  {
    "date": "2009-01",
    "price": 380300
  },
  {
    "date": "2009-02",
    "price": 377300
  },
  {
    "date": "2009-03",
    "price": 374300
  },
  {
    "date": "2009-04",
    "price": 370900
  },
  {
    "date": "2009-05",
    "price": 366800
  },
  {
    "date": "2009-06",
    "price": 363000
  },
  {
    "date": "2009-07",
    "price": 359400
  },
  {
    "date": "2009-08",
    "price": 355600
  },
  {
    "date": "2009-09",
    "price": 352200
  },
  {
    "date": "2009-10",
    "price": 349900
  },
  {
    "date": "2009-11",
    "price": 348400
  },
  {
    "date": "2009-12",
    "price": 347200
  },
  {
    "date": "2010-01",
    "price": 346300
  },
  {
    "date": "2010-02",
    "price": 346300
  },
  {
    "date": "2010-03",
    "price": 344500
  },
  {
    "date": "2010-04",
    "price": 341500
  },
  {
    "date": "2010-05",
    "price": 338600
  },
  {
    "date": "2010-06",
    "price": 338100
  },
  {
    "date": "2010-07",
    "price": 336400
  },
  {
    "date": "2010-08",
    "price": 333700
  },
  {
    "date": "2010-09",
    "price": 331700
  },
  {
    "date": "2010-10",
    "price": 330800
  },
  {
    "date": "2010-11",
    "price": 329200
  },
  {
    "date": "2010-12",
    "price": 326600
  },
  {
    "date": "2011-01",
    "price": 323500
  },
  {
    "date": "2011-02",
    "price": 320800
  },
  {
    "date": "2011-03",
    "price": 318700
  },
  {
    "date": "2011-04",
    "price": 317600
  },
  {
    "date": "2011-05",
    "price": 317400
  },
  {
    "date": "2011-06",
    "price": 315400
  },
  {
    "date": "2011-07",
    "price": 313000
  },
  {
    "date": "2011-08",
    "price": 311400
  },
  {
    "date": "2011-09",
    "price": 309800
  },
  {
    "date": "2011-10",
    "price": 309600
  },
  {
    "date": "2011-11",
    "price": 308900
  },
  {
    "date": "2011-12",
    "price": 306300
  },
  {
    "date": "2012-01",
    "price": 303800
  },
  {
    "date": "2012-02",
    "price": 301000
  },
  {
    "date": "2012-03",
    "price": 297600
  },
  {
    "date": "2012-04",
    "price": 294600
  },
  {
    "date": "2012-05",
    "price": 291900
  },
  {
    "date": "2012-06",
    "price": 289700
  },
  {
    "date": "2012-07",
    "price": 291000
  },
  {
    "date": "2012-08",
    "price": 294600
  },
  {
    "date": "2012-09",
    "price": 297300
  },
  {
    "date": "2012-10",
    "price": 295700
  },
  {
    "date": "2012-11",
    "price": 292900
  },
  {
    "date": "2012-12",
    "price": 290900
  },
  {
    "date": "2013-01",
    "price": 291500
  },
  {
    "date": "2013-02",
    "price": 291700
  },
  {
    "date": "2013-03",
    "price": 291200
  },
  {
    "date": "2013-04",
    "price": 292700
  },
  {
    "date": "2013-05",
    "price": 296100
  },
  {
    "date": "2013-06",
    "price": 296600
  },
  {
    "date": "2013-07",
    "price": 293000
  },
  {
    "date": "2013-08",
    "price": 289300
  },
  {
    "date": "2013-09",
    "price": 286600
  },
  {
    "date": "2013-10",
    "price": 283200
  },
  {
    "date": "2013-11",
    "price": 280200
  },
  {
    "date": "2013-12",
    "price": 279400
  },
  {
    "date": "2014-01",
    "price": 278200
  },
  {
    "date": "2014-02",
    "price": 276700
  },
  {
    "date": "2014-03",
    "price": 276300
  },
  {
    "date": "2014-04",
    "price": 275700
  },
  {
    "date": "2014-05",
    "price": 275500
  },
  {
    "date": "2014-06",
    "price": 276000
  },
  {
    "date": "2014-07",
    "price": 276000
  },
  {
    "date": "2014-08",
    "price": 276000
  },
  {
    "date": "2014-09",
    "price": 277200
  },
  {
    "date": "2014-10",
    "price": 277200
  },
  {
    "date": "2014-11",
    "price": 275700
  },
  {
    "date": "2014-12",
    "price": 275000
  },
  {
    "date": "2015-01",
    "price": 274100
  },
  {
    "date": "2015-02",
    "price": 274900
  },
  {
    "date": "2015-03",
    "price": 278100
  },
  {
    "date": "2015-04",
    "price": 280200
  },
  {
    "date": "2015-05",
    "price": 279300
  },
  {
    "date": "2015-06",
    "price": 279100
  },
  {
    "date": "2015-07",
    "price": 282000
  },
  {
    "date": "2015-08",
    "price": 285300
  },
  {
    "date": "2015-09",
    "price": 285800
  },
  {
    "date": "2015-10",
    "price": 285400
  },
  {
    "date": "2015-11",
    "price": 287400
  },
  {
    "date": "2015-12",
    "price": 290500
  },
  {
    "date": "2016-01",
    "price": 291600
  },
  {
    "date": "2016-02",
    "price": 290500
  },
  {
    "date": "2016-03",
    "price": 289600
  },
  {
    "date": "2016-04",
    "price": 289900
  },
  {
    "date": "2016-05",
    "price": 289100
  },
  {
    "date": "2016-06",
    "price": 288500
  },
  {
    "date": "2016-07",
    "price": 290600
  },
  {
    "date": "2016-08",
    "price": 292100
  },
  {
    "date": "2016-09",
    "price": 291100
  },
  {
    "date": "2016-10",
    "price": 290000
  },
  {
    "date": "2016-11",
    "price": 287400
  },
  {
    "date": "2016-12",
    "price": 282400
  },
  {
    "date": "2017-01",
    "price": 279400
  },
  {
    "date": "2017-02",
    "price": 279500
  },
  {
    "date": "2017-03",
    "price": 280500
  },
  {
    "date": "2017-04",
    "price": 281700
  },
  {
    "date": "2017-05",
    "price": 283600
  },
  {
    "date": "2017-06",
    "price": 286700
  },
  {
    "date": "2017-07",
    "price": 286200
  },
  {
    "date": "2017-08",
    "price": 279800
  },
  {
    "date": "2017-09",
    "price": 270200
  },
  {
    "date": "2017-10",
    "price": 266000
  },
  {
    "date": "2017-11",
    "price": 268900
  },
  {
    "date": "2017-12",
    "price": 274800
  },
  {
    "date": "2018-01",
    "price": 278500
  },
  {
    "date": "2018-02",
    "price": 281300
  },
  {
    "date": "2018-03",
    "price": 282700
  },
  {
    "date": "2018-04",
    "price": 281200
  },
  {
    "date": "2018-05",
    "price": 279000
  },
  {
    "date": "2018-06",
    "price": 276600
  },
  {
    "date": "2018-07",
    "price": 274200
  },
  {
    "date": "2018-08",
    "price": 273000
  },
  {
    "date": "2018-09",
    "price": 277300
  },
  {
    "date": "2018-10",
    "price": 284100
  },
  {
    "date": "2018-11",
    "price": 289300
  },
  {
    "date": "2018-12",
    "price": 291800
  },
  {
    "date": "2019-01",
    "price": 294400
  },
  {
    "date": "2019-02",
    "price": 295500
  },
  {
    "date": "2019-03",
    "price": 294100
  },
  {
    "date": "2019-04",
    "price": 292200
  }
]