[
  {
    "date": "1996-04",
    "price": 602500
  },
  {
    "date": "1996-05",
    "price": 606600
  },
  {
    "date": "1996-06",
    "price": 610800
  },
  {
    "date": "1996-07",
    "price": 615100
  },
  {
    "date": "1996-08",
    "price": 619300
  },
  {
    "date": "1996-09",
    "price": 623500
  },
  {
    "date": "1996-10",
    "price": 627900
  },
  {
    "date": "1996-11",
    "price": 632300
  },
  {
    "date": "1996-12",
    "price": 637400
  },
  {
    "date": "1997-01",
    "price": 643000
  },
  {
    "date": "1997-02",
    "price": 648200
  },
  {
    "date": "1997-03",
    "price": 652700
  },
  {
    "date": "1997-04",
    "price": 657500
  },
  {
    "date": "1997-05",
    "price": 662500
  },
  {
    "date": "1997-06",
    "price": 667500
  },
  {
    "date": "1997-07",
    "price": 672600
  },
  {
    "date": "1997-08",
    "price": 677500
  },
  {
    "date": "1997-09",
    "price": 682400
  },
  {
    "date": "1997-10",
    "price": 687500
  },
  {
    "date": "1997-11",
    "price": 692600
  },
  {
    "date": "1997-12",
    "price": 698500
  },
  {
    "date": "1998-01",
    "price": 705000
  },
  {
    "date": "1998-02",
    "price": 711200
  },
  {
    "date": "1998-03",
    "price": 716900
  },
  {
    "date": "1998-04",
    "price": 723100
  },
  {
    "date": "1998-05",
    "price": 729600
  },
  {
    "date": "1998-06",
    "price": 736600
  },
  {
    "date": "1998-07",
    "price": 743600
  },
  {
    "date": "1998-08",
    "price": 750700
  },
  {
    "date": "1998-09",
    "price": 757800
  },
  {
    "date": "1998-10",
    "price": 765100
  },
  {
    "date": "1998-11",
    "price": 772400
  },
  {
    "date": "1998-12",
    "price": 780500
  },
  {
    "date": "1999-01",
    "price": 789100
  },
  {
    "date": "1999-02",
    "price": 797100
  },
  {
    "date": "1999-03",
    "price": 804700
  },
  {
    "date": "1999-04",
    "price": 812500
  },
  {
    "date": "1999-05",
    "price": 820600
  },
  {
    "date": "1999-06",
    "price": 828700
  },
  {
    "date": "1999-07",
    "price": 836800
  },
  {
    "date": "1999-08",
    "price": 844800
  },
  {
    "date": "1999-09",
    "price": 852500
  },
  {
    "date": "1999-10",
    "price": 860200
  },
  {
    "date": "1999-11",
    "price": 867900
  },
  {
    "date": "1999-12",
    "price": 876100
  },
  {
    "date": "2000-01",
    "price": 884600
  },
  {
    "date": "2000-02",
    "price": 892800
  },
  {
    "date": "2000-03",
    "price": 900200
  },
  {
    "date": "2000-04",
    "price": 907800
  },
  {
    "date": "2000-05",
    "price": 915600
  },
  {
    "date": "2000-06",
    "price": 923300
  },
  {
    "date": "2000-07",
    "price": 930900
  },
  {
    "date": "2000-08",
    "price": 938300
  },
  {
    "date": "2000-09",
    "price": 945400
  },
  {
    "date": "2000-10",
    "price": 952700
  },
  {
    "date": "2000-11",
    "price": 959900
  },
  {
    "date": "2000-12",
    "price": 967400
  },
  {
    "date": "2001-01",
    "price": 975200
  },
  {
    "date": "2001-02",
    "price": 982900
  },
  {
    "date": "2001-03",
    "price": 990700
  },
  {
    "date": "2001-04",
    "price": 998900
  },
  {
    "date": "2001-05",
    "price": 1007500
  },
  {
    "date": "2001-06",
    "price": 1016500
  },
  {
    "date": "2001-07",
    "price": 1025500
  },
  {
    "date": "2001-08",
    "price": 1034400
  },
  {
    "date": "2001-09",
    "price": 1043100
  },
  {
    "date": "2001-10",
    "price": 1052200
  },
  {
    "date": "2001-11",
    "price": 1061500
  },
  {
    "date": "2001-12",
    "price": 1070900
  },
  {
    "date": "2002-01",
    "price": 1080600
  },
  {
    "date": "2002-02",
    "price": 1090600
  },
  {
    "date": "2002-03",
    "price": 1101100
  },
  {
    "date": "2002-04",
    "price": 1112300
  },
  {
    "date": "2002-05",
    "price": 1124000
  },
  {
    "date": "2002-06",
    "price": 1136200
  },
  {
    "date": "2002-07",
    "price": 1148500
  },
  {
    "date": "2002-08",
    "price": 1160700
  },
  {
    "date": "2002-09",
    "price": 1172700
  },
  {
    "date": "2002-10",
    "price": 1184400
  },
  {
    "date": "2002-11",
    "price": 1198000
  },
  {
    "date": "2002-12",
    "price": 1216500
  },
  {
    "date": "2003-01",
    "price": 1238600
  },
  {
    "date": "2003-02",
    "price": 1260600
  },
  {
    "date": "2003-03",
    "price": 1281800
  },
  {
    "date": "2003-04",
    "price": 1301300
  },
  {
    "date": "2003-05",
    "price": 1317000
  },
  {
    "date": "2003-06",
    "price": 1329100
  },
  {
    "date": "2003-07",
    "price": 1339200
  },
  {
    "date": "2003-08",
    "price": 1349600
  },
  {
    "date": "2003-09",
    "price": 1362400
  },
  {
    "date": "2003-10",
    "price": 1377300
  },
  {
    "date": "2003-11",
    "price": 1392200
  },
  {
    "date": "2003-12",
    "price": 1405800
  },
  {
    "date": "2004-01",
    "price": 1418100
  },
  {
    "date": "2004-02",
    "price": 1430000
  },
  {
    "date": "2004-03",
    "price": 1442700
  },
  {
    "date": "2004-04",
    "price": 1457700
  },
  {
    "date": "2004-05",
    "price": 1476300
  },
  {
    "date": "2004-06",
    "price": 1498900
  },
  {
    "date": "2004-07",
    "price": 1524100
  },
  {
    "date": "2004-08",
    "price": 1549200
  },
  {
    "date": "2004-09",
    "price": 1571900
  },
  {
    "date": "2004-10",
    "price": 1592200
  },
  {
    "date": "2004-11",
    "price": 1610500
  },
  {
    "date": "2004-12",
    "price": 1627300
  },
  {
    "date": "2005-01",
    "price": 1643200
  },
  {
    "date": "2005-02",
    "price": 1659000
  },
  {
    "date": "2005-03",
    "price": 1675500
  },
  {
    "date": "2005-04",
    "price": 1692100
  },
  {
    "date": "2005-05",
    "price": 1706900
  },
  {
    "date": "2005-06",
    "price": 1719900
  },
  {
    "date": "2005-07",
    "price": 1731600
  },
  {
    "date": "2005-08",
    "price": 1742500
  },
  {
    "date": "2005-09",
    "price": 1753100
  },
  {
    "date": "2005-10",
    "price": 1763200
  },
  {
    "date": "2005-11",
    "price": 1772300
  },
  {
    "date": "2005-12",
    "price": 1780400
  },
  {
    "date": "2006-01",
    "price": 1787800
  },
  {
    "date": "2006-02",
    "price": 1794100
  },
  {
    "date": "2006-03",
    "price": 1799800
  },
  {
    "date": "2006-04",
    "price": 1804300
  },
  {
    "date": "2006-05",
    "price": 1806700
  },
  {
    "date": "2006-06",
    "price": 1807700
  },
  {
    "date": "2006-07",
    "price": 1807900
  },
  {
    "date": "2006-08",
    "price": 1807600
  },
  {
    "date": "2006-09",
    "price": 1808100
  },
  {
    "date": "2006-10",
    "price": 1809300
  },
  {
    "date": "2006-11",
    "price": 1809900
  },
  {
    "date": "2006-12",
    "price": 1808900
  },
  {
    "date": "2007-01",
    "price": 1806500
  },
  {
    "date": "2007-02",
    "price": 1802900
  },
  {
    "date": "2007-03",
    "price": 1800200
  },
  {
    "date": "2007-04",
    "price": 1797900
  },
  {
    "date": "2007-05",
    "price": 1794100
  },
  {
    "date": "2007-06",
    "price": 1788300
  },
  {
    "date": "2007-07",
    "price": 1781400
  },
  {
    "date": "2007-08",
    "price": 1773900
  },
  {
    "date": "2007-09",
    "price": 1767900
  },
  {
    "date": "2007-10",
    "price": 1763200
  },
  {
    "date": "2007-11",
    "price": 1760000
  },
  {
    "date": "2007-12",
    "price": 1758300
  },
  {
    "date": "2008-01",
    "price": 1757400
  },
  {
    "date": "2008-02",
    "price": 1755000
  },
  {
    "date": "2008-03",
    "price": 1752700
  },
  {
    "date": "2008-04",
    "price": 1748400
  },
  {
    "date": "2008-05",
    "price": 1740000
  },
  {
    "date": "2008-06",
    "price": 1726800
  },
  {
    "date": "2008-07",
    "price": 1711800
  },
  {
    "date": "2008-08",
    "price": 1696300
  },
  {
    "date": "2008-09",
    "price": 1683300
  },
  {
    "date": "2008-10",
    "price": 1671400
  },
  {
    "date": "2008-11",
    "price": 1659900
  },
  {
    "date": "2008-12",
    "price": 1649200
  },
  {
    "date": "2009-01",
    "price": 1640000
  },
  {
    "date": "2009-02",
    "price": 1631200
  },
  {
    "date": "2009-03",
    "price": 1624500
  },
  {
    "date": "2009-04",
    "price": 1617200
  },
  {
    "date": "2009-05",
    "price": 1606500
  },
  {
    "date": "2009-06",
    "price": 1593900
  },
  {
    "date": "2009-07",
    "price": 1584500
  },
  {
    "date": "2009-08",
    "price": 1578500
  },
  {
    "date": "2009-09",
    "price": 1577900
  },
  {
    "date": "2009-10",
    "price": 1581600
  },
  {
    "date": "2009-11",
    "price": 1587800
  },
  {
    "date": "2009-12",
    "price": 1594100
  },
  {
    "date": "2010-01",
    "price": 1600100
  },
  {
    "date": "2010-02",
    "price": 1607300
  },
  {
    "date": "2010-03",
    "price": 1603100
  },
  {
    "date": "2010-04",
    "price": 1584400
  },
  {
    "date": "2010-05",
    "price": 1570900
  },
  {
    "date": "2010-06",
    "price": 1570200
  },
  {
    "date": "2010-07",
    "price": 1568700
  },
  {
    "date": "2010-08",
    "price": 1567200
  },
  {
    "date": "2010-09",
    "price": 1565400
  },
  {
    "date": "2010-10",
    "price": 1566900
  },
  {
    "date": "2010-11",
    "price": 1566300
  },
  {
    "date": "2010-12",
    "price": 1561800
  },
  {
    "date": "2011-01",
    "price": 1554000
  },
  {
    "date": "2011-02",
    "price": 1547200
  },
  {
    "date": "2011-03",
    "price": 1535700
  },
  {
    "date": "2011-04",
    "price": 1532200
  },
  {
    "date": "2011-05",
    "price": 1534300
  },
  {
    "date": "2011-06",
    "price": 1543200
  },
  {
    "date": "2011-07",
    "price": 1554300
  },
  {
    "date": "2011-08",
    "price": 1555900
  },
  {
    "date": "2011-09",
    "price": 1546200
  },
  {
    "date": "2011-10",
    "price": 1538200
  },
  {
    "date": "2011-11",
    "price": 1532700
  },
  {
    "date": "2011-12",
    "price": 1523400
  },
  {
    "date": "2012-01",
    "price": 1511900
  },
  {
    "date": "2012-02",
    "price": 1501200
  },
  {
    "date": "2012-03",
    "price": 1499000
  },
  {
    "date": "2012-04",
    "price": 1506200
  },
  {
    "date": "2012-05",
    "price": 1522300
  },
  {
    "date": "2012-06",
    "price": 1532200
  },
  {
    "date": "2012-07",
    "price": 1540300
  },
  {
    "date": "2012-08",
    "price": 1553600
  },
  {
    "date": "2012-09",
    "price": 1566600
  },
  {
    "date": "2012-10",
    "price": 1570100
  },
  {
    "date": "2012-11",
    "price": 1575800
  },
  {
    "date": "2012-12",
    "price": 1579000
  },
  {
    "date": "2013-01",
    "price": 1580600
  },
  {
    "date": "2013-02",
    "price": 1593600
  },
  {
    "date": "2013-03",
    "price": 1615900
  },
  {
    "date": "2013-04",
    "price": 1633000
  },
  {
    "date": "2013-05",
    "price": 1642900
  },
  {
    "date": "2013-06",
    "price": 1653100
  },
  {
    "date": "2013-07",
    "price": 1661200
  },
  {
    "date": "2013-08",
    "price": 1663600
  },
  {
    "date": "2013-09",
    "price": 1665300
  },
  {
    "date": "2013-10",
    "price": 1670400
  },
  {
    "date": "2013-11",
    "price": 1674600
  },
  {
    "date": "2013-12",
    "price": 1688100
  },
  {
    "date": "2014-01",
    "price": 1707400
  },
  {
    "date": "2014-02",
    "price": 1716000
  },
  {
    "date": "2014-03",
    "price": 1714500
  },
  {
    "date": "2014-04",
    "price": 1724400
  },
  {
    "date": "2014-05",
    "price": 1735800
  },
  {
    "date": "2014-06",
    "price": 1750900
  },
  {
    "date": "2014-07",
    "price": 1763900
  },
  {
    "date": "2014-08",
    "price": 1787000
  },
  {
    "date": "2014-09",
    "price": 1804400
  },
  {
    "date": "2014-10",
    "price": 1810600
  },
  {
    "date": "2014-11",
    "price": 1807700
  },
  {
    "date": "2014-12",
    "price": 1809300
  },
  {
    "date": "2015-01",
    "price": 1813400
  },
  {
    "date": "2015-02",
    "price": 1823200
  },
  {
    "date": "2015-03",
    "price": 1841800
  },
  {
    "date": "2015-04",
    "price": 1853100
  },
  {
    "date": "2015-05",
    "price": 1854100
  },
  {
    "date": "2015-06",
    "price": 1848400
  },
  {
    "date": "2015-07",
    "price": 1851400
  },
  {
    "date": "2015-08",
    "price": 1860200
  },
  {
    "date": "2015-09",
    "price": 1880800
  },
  {
    "date": "2015-10",
    "price": 1901100
  },
  {
    "date": "2015-11",
    "price": 1914700
  },
  {
    "date": "2015-12",
    "price": 1920200
  },
  {
    "date": "2016-01",
    "price": 1930100
  },
  {
    "date": "2016-02",
    "price": 1940200
  },
  {
    "date": "2016-03",
    "price": 1952000
  },
  {
    "date": "2016-04",
    "price": 1956800
  },
  {
    "date": "2016-05",
    "price": 1961600
  },
  {
    "date": "2016-06",
    "price": 1965400
  },
  {
    "date": "2016-07",
    "price": 1971200
  },
  {
    "date": "2016-08",
    "price": 1979700
  },
  {
    "date": "2016-09",
    "price": 1992400
  },
  {
    "date": "2016-10",
    "price": 1998800
  },
  {
    "date": "2016-11",
    "price": 2003500
  },
  {
    "date": "2016-12",
    "price": 2022000
  },
  {
    "date": "2017-01",
    "price": 2047800
  },
  {
    "date": "2017-02",
    "price": 2066000
  },
  {
    "date": "2017-03",
    "price": 2073900
  },
  {
    "date": "2017-04",
    "price": 2080900
  },
  {
    "date": "2017-05",
    "price": 2089000
  },
  {
    "date": "2017-06",
    "price": 2097700
  },
  {
    "date": "2017-07",
    "price": 2111700
  },
  {
    "date": "2017-08",
    "price": 2131100
  },
  {
    "date": "2017-09",
    "price": 2152900
  },
  {
    "date": "2017-10",
    "price": 2174200
  },
  {
    "date": "2017-11",
    "price": 2192500
  },
  {
    "date": "2017-12",
    "price": 2210900
  },
  {
    "date": "2018-01",
    "price": 2224200
  },
  {
    "date": "2018-02",
    "price": 2223000
  },
  {
    "date": "2018-03",
    "price": 2221800
  },
  {
    "date": "2018-04",
    "price": 2239400
  },
  {
    "date": "2018-05",
    "price": 2267300
  },
  {
    "date": "2018-06",
    "price": 2287800
  },
  {
    "date": "2018-07",
    "price": 2299400
  },
  {
    "date": "2018-08",
    "price": 2294000
  },
  {
    "date": "2018-09",
    "price": 2282300
  },
  {
    "date": "2018-10",
    "price": 2281300
  },
  {
    "date": "2018-11",
    "price": 2300000
  },
  {
    "date": "2018-12",
    "price": 2314100
  },
  {
    "date": "2019-01",
    "price": 2319600
  },
  {
    "date": "2019-02",
    "price": 2326900
  },
  {
    "date": "2019-03",
    "price": 2344900
  },
  {
    "date": "2019-04",
    "price": 2359100
  }
]