[
  {
    "date": "1996-04",
    "price": 363600
  },
  {
    "date": "1996-05",
    "price": 366200
  },
  {
    "date": "1996-06",
    "price": 368800
  },
  {
    "date": "1996-07",
    "price": 371500
  },
  {
    "date": "1996-08",
    "price": 374200
  },
  {
    "date": "1996-09",
    "price": 376800
  },
  {
    "date": "1996-10",
    "price": 379500
  },
  {
    "date": "1996-11",
    "price": 382100
  },
  {
    "date": "1996-12",
    "price": 384900
  },
  {
    "date": "1997-01",
    "price": 387800
  },
  {
    "date": "1997-02",
    "price": 390500
  },
  {
    "date": "1997-03",
    "price": 393100
  },
  {
    "date": "1997-04",
    "price": 395800
  },
  {
    "date": "1997-05",
    "price": 398300
  },
  {
    "date": "1997-06",
    "price": 400800
  },
  {
    "date": "1997-07",
    "price": 403200
  },
  {
    "date": "1997-08",
    "price": 405500
  },
  {
    "date": "1997-09",
    "price": 407500
  },
  {
    "date": "1997-10",
    "price": 409300
  },
  {
    "date": "1997-11",
    "price": 410800
  },
  {
    "date": "1997-12",
    "price": 412200
  },
  {
    "date": "1998-01",
    "price": 413500
  },
  {
    "date": "1998-02",
    "price": 414600
  },
  {
    "date": "1998-03",
    "price": 415200
  },
  {
    "date": "1998-04",
    "price": 415500
  },
  {
    "date": "1998-05",
    "price": 415700
  },
  {
    "date": "1998-06",
    "price": 415600
  },
  {
    "date": "1998-07",
    "price": 415200
  },
  {
    "date": "1998-08",
    "price": 414600
  },
  {
    "date": "1998-09",
    "price": 413800
  },
  {
    "date": "1998-10",
    "price": 412700
  },
  {
    "date": "1998-11",
    "price": 411400
  },
  {
    "date": "1998-12",
    "price": 410100
  },
  {
    "date": "1999-01",
    "price": 408800
  },
  {
    "date": "1999-02",
    "price": 407600
  },
  {
    "date": "1999-03",
    "price": 406300
  },
  {
    "date": "1999-04",
    "price": 405100
  },
  {
    "date": "1999-05",
    "price": 404100
  },
  {
    "date": "1999-06",
    "price": 403400
  },
  {
    "date": "1999-07",
    "price": 403000
  },
  {
    "date": "1999-08",
    "price": 402900
  },
  {
    "date": "1999-09",
    "price": 403000
  },
  {
    "date": "1999-10",
    "price": 403500
  },
  {
    "date": "1999-11",
    "price": 404200
  },
  {
    "date": "1999-12",
    "price": 405200
  },
  {
    "date": "2000-01",
    "price": 406700
  },
  {
    "date": "2000-02",
    "price": 408500
  },
  {
    "date": "2000-03",
    "price": 410500
  },
  {
    "date": "2000-04",
    "price": 412900
  },
  {
    "date": "2000-05",
    "price": 415600
  },
  {
    "date": "2000-06",
    "price": 418400
  },
  {
    "date": "2000-07",
    "price": 421500
  },
  {
    "date": "2000-08",
    "price": 424700
  },
  {
    "date": "2000-09",
    "price": 427900
  },
  {
    "date": "2000-10",
    "price": 431100
  },
  {
    "date": "2000-11",
    "price": 434100
  },
  {
    "date": "2000-12",
    "price": 437100
  },
  {
    "date": "2001-01",
    "price": 440000
  },
  {
    "date": "2001-02",
    "price": 442900
  },
  {
    "date": "2001-03",
    "price": 445700
  },
  {
    "date": "2001-04",
    "price": 448600
  },
  {
    "date": "2001-05",
    "price": 451400
  },
  {
    "date": "2001-06",
    "price": 454300
  },
  {
    "date": "2001-07",
    "price": 457300
  },
  {
    "date": "2001-08",
    "price": 460100
  },
  {
    "date": "2001-09",
    "price": 462900
  },
  {
    "date": "2001-10",
    "price": 465500
  },
  {
    "date": "2001-11",
    "price": 468000
  },
  {
    "date": "2001-12",
    "price": 470400
  },
  {
    "date": "2002-01",
    "price": 472600
  },
  {
    "date": "2002-02",
    "price": 475000
  },
  {
    "date": "2002-03",
    "price": 477500
  },
  {
    "date": "2002-04",
    "price": 480200
  },
  {
    "date": "2002-05",
    "price": 482900
  },
  {
    "date": "2002-06",
    "price": 485800
  },
  {
    "date": "2002-07",
    "price": 488800
  },
  {
    "date": "2002-08",
    "price": 491900
  },
  {
    "date": "2002-09",
    "price": 494900
  },
  {
    "date": "2002-10",
    "price": 497700
  },
  {
    "date": "2002-11",
    "price": 500700
  },
  {
    "date": "2002-12",
    "price": 503800
  },
  {
    "date": "2003-01",
    "price": 506400
  },
  {
    "date": "2003-02",
    "price": 508100
  },
  {
    "date": "2003-03",
    "price": 509500
  },
  {
    "date": "2003-04",
    "price": 510500
  },
  {
    "date": "2003-05",
    "price": 511400
  },
  {
    "date": "2003-06",
    "price": 512400
  },
  {
    "date": "2003-07",
    "price": 513600
  },
  {
    "date": "2003-08",
    "price": 515000
  },
  {
    "date": "2003-09",
    "price": 516400
  },
  {
    "date": "2003-10",
    "price": 517900
  },
  {
    "date": "2003-11",
    "price": 519400
  },
  {
    "date": "2003-12",
    "price": 520600
  },
  {
    "date": "2004-01",
    "price": 521600
  },
  {
    "date": "2004-02",
    "price": 522700
  },
  {
    "date": "2004-03",
    "price": 524100
  },
  {
    "date": "2004-04",
    "price": 525800
  },
  {
    "date": "2004-05",
    "price": 527800
  },
  {
    "date": "2004-06",
    "price": 530000
  },
  {
    "date": "2004-07",
    "price": 532300
  },
  {
    "date": "2004-08",
    "price": 534300
  },
  {
    "date": "2004-09",
    "price": 536100
  },
  {
    "date": "2004-10",
    "price": 537600
  },
  {
    "date": "2004-11",
    "price": 539100
  },
  {
    "date": "2004-12",
    "price": 540700
  },
  {
    "date": "2005-01",
    "price": 542000
  },
  {
    "date": "2005-02",
    "price": 542100
  },
  {
    "date": "2005-03",
    "price": 540400
  },
  {
    "date": "2005-04",
    "price": 536900
  },
  {
    "date": "2005-05",
    "price": 531800
  },
  {
    "date": "2005-06",
    "price": 525300
  },
  {
    "date": "2005-07",
    "price": 517800
  },
  {
    "date": "2005-08",
    "price": 510100
  },
  {
    "date": "2005-09",
    "price": 503400
  },
  {
    "date": "2005-10",
    "price": 498400
  },
  {
    "date": "2005-11",
    "price": 495200
  },
  {
    "date": "2005-12",
    "price": 493800
  },
  {
    "date": "2006-01",
    "price": 493800
  },
  {
    "date": "2006-02",
    "price": 495300
  },
  {
    "date": "2006-03",
    "price": 498500
  },
  {
    "date": "2006-04",
    "price": 503100
  },
  {
    "date": "2006-05",
    "price": 507700
  },
  {
    "date": "2006-06",
    "price": 511000
  },
  {
    "date": "2006-07",
    "price": 513300
  },
  {
    "date": "2006-08",
    "price": 515000
  },
  {
    "date": "2006-09",
    "price": 516400
  },
  {
    "date": "2006-10",
    "price": 516600
  },
  {
    "date": "2006-11",
    "price": 515200
  },
  {
    "date": "2006-12",
    "price": 512900
  },
  {
    "date": "2007-01",
    "price": 510700
  },
  {
    "date": "2007-02",
    "price": 508600
  },
  {
    "date": "2007-03",
    "price": 506600
  },
  {
    "date": "2007-04",
    "price": 504600
  },
  {
    "date": "2007-05",
    "price": 502100
  },
  {
    "date": "2007-06",
    "price": 498900
  },
  {
    "date": "2007-07",
    "price": 495400
  },
  {
    "date": "2007-08",
    "price": 491900
  },
  {
    "date": "2007-09",
    "price": 487900
  },
  {
    "date": "2007-10",
    "price": 482700
  },
  {
    "date": "2007-11",
    "price": 476600
  },
  {
    "date": "2007-12",
    "price": 470800
  },
  {
    "date": "2008-01",
    "price": 465600
  },
  {
    "date": "2008-02",
    "price": 460000
  },
  {
    "date": "2008-03",
    "price": 453500
  },
  {
    "date": "2008-04",
    "price": 445900
  },
  {
    "date": "2008-05",
    "price": 438000
  },
  {
    "date": "2008-06",
    "price": 430900
  },
  {
    "date": "2008-07",
    "price": 426500
  },
  {
    "date": "2008-08",
    "price": 425000
  },
  {
    "date": "2008-09",
    "price": 424900
  },
  {
    "date": "2008-10",
    "price": 424700
  },
  {
    "date": "2008-11",
    "price": 424500
  },
  {
    "date": "2008-12",
    "price": 425100
  },
  {
    "date": "2009-01",
    "price": 426300
  },
  {
    "date": "2009-02",
    "price": 427500
  },
  {
    "date": "2009-03",
    "price": 428200
  },
  {
    "date": "2009-04",
    "price": 427800
  },
  {
    "date": "2009-05",
    "price": 426300
  },
  {
    "date": "2009-06",
    "price": 423400
  },
  {
    "date": "2009-07",
    "price": 420500
  },
  {
    "date": "2009-08",
    "price": 419100
  },
  {
    "date": "2009-09",
    "price": 420400
  },
  {
    "date": "2009-10",
    "price": 423600
  },
  {
    "date": "2009-11",
    "price": 427500
  },
  {
    "date": "2009-12",
    "price": 431700
  },
  {
    "date": "2010-01",
    "price": 435800
  },
  {
    "date": "2010-02",
    "price": 439300
  },
  {
    "date": "2010-03",
    "price": 439100
  },
  {
    "date": "2010-04",
    "price": 436100
  },
  {
    "date": "2010-05",
    "price": 435000
  },
  {
    "date": "2010-06",
    "price": 437000
  },
  {
    "date": "2010-07",
    "price": 438400
  },
  {
    "date": "2010-08",
    "price": 438800
  },
  {
    "date": "2010-09",
    "price": 437300
  },
  {
    "date": "2010-10",
    "price": 436700
  },
  {
    "date": "2010-11",
    "price": 437100
  },
  {
    "date": "2010-12",
    "price": 435100
  },
  {
    "date": "2011-01",
    "price": 429100
  },
  {
    "date": "2011-02",
    "price": 425200
  },
  {
    "date": "2011-03",
    "price": 425200
  },
  {
    "date": "2011-04",
    "price": 426300
  },
  {
    "date": "2011-05",
    "price": 429400
  },
  {
    "date": "2011-06",
    "price": 437300
  },
  {
    "date": "2011-07",
    "price": 446000
  },
  {
    "date": "2011-08",
    "price": 450000
  },
  {
    "date": "2011-09",
    "price": 450100
  },
  {
    "date": "2011-10",
    "price": 449900
  },
  {
    "date": "2011-11",
    "price": 449400
  },
  {
    "date": "2011-12",
    "price": 447600
  },
  {
    "date": "2012-01",
    "price": 444400
  },
  {
    "date": "2012-02",
    "price": 440100
  },
  {
    "date": "2012-03",
    "price": 439900
  },
  {
    "date": "2012-04",
    "price": 447200
  },
  {
    "date": "2012-05",
    "price": 455000
  },
  {
    "date": "2012-06",
    "price": 458600
  },
  {
    "date": "2012-07",
    "price": 459300
  },
  {
    "date": "2012-08",
    "price": 456900
  },
  {
    "date": "2012-09",
    "price": 454300
  },
  {
    "date": "2012-10",
    "price": 452500
  },
  {
    "date": "2012-11",
    "price": 448100
  },
  {
    "date": "2012-12",
    "price": 445300
  },
  {
    "date": "2013-01",
    "price": 448800
  },
  {
    "date": "2013-02",
    "price": 450400
  },
  {
    "date": "2013-03",
    "price": 446100
  },
  {
    "date": "2013-04",
    "price": 441000
  },
  {
    "date": "2013-05",
    "price": 437900
  },
  {
    "date": "2013-06",
    "price": 435300
  },
  {
    "date": "2013-07",
    "price": 436000
  },
  {
    "date": "2013-08",
    "price": 439800
  },
  {
    "date": "2013-09",
    "price": 442500
  },
  {
    "date": "2013-10",
    "price": 443000
  },
  {
    "date": "2013-11",
    "price": 445900
  },
  {
    "date": "2013-12",
    "price": 449900
  },
  {
    "date": "2014-01",
    "price": 451500
  },
  {
    "date": "2014-02",
    "price": 454600
  },
  {
    "date": "2014-03",
    "price": 461100
  },
  {
    "date": "2014-04",
    "price": 466700
  },
  {
    "date": "2014-05",
    "price": 469800
  },
  {
    "date": "2014-06",
    "price": 469500
  },
  {
    "date": "2014-07",
    "price": 465800
  },
  {
    "date": "2014-08",
    "price": 464300
  },
  {
    "date": "2014-09",
    "price": 466500
  },
  {
    "date": "2014-10",
    "price": 467300
  },
  {
    "date": "2014-11",
    "price": 466500
  },
  {
    "date": "2014-12",
    "price": 464700
  },
  {
    "date": "2015-01",
    "price": 464100
  },
  {
    "date": "2015-02",
    "price": 465500
  },
  {
    "date": "2015-03",
    "price": 466700
  },
  {
    "date": "2015-04",
    "price": 465800
  },
  {
    "date": "2015-05",
    "price": 466400
  },
  {
    "date": "2015-06",
    "price": 470000
  },
  {
    "date": "2015-07",
    "price": 473300
  },
  {
    "date": "2015-08",
    "price": 474800
  },
  {
    "date": "2015-09",
    "price": 475300
  },
  {
    "date": "2015-10",
    "price": 475900
  },
  {
    "date": "2015-11",
    "price": 476000
  },
  {
    "date": "2015-12",
    "price": 476400
  },
  {
    "date": "2016-01",
    "price": 477200
  },
  {
    "date": "2016-02",
    "price": 478100
  },
  {
    "date": "2016-03",
    "price": 478000
  },
  {
    "date": "2016-04",
    "price": 477400
  },
  {
    "date": "2016-05",
    "price": 478100
  },
  {
    "date": "2016-06",
    "price": 480900
  },
  {
    "date": "2016-07",
    "price": 484900
  },
  {
    "date": "2016-08",
    "price": 488200
  },
  {
    "date": "2016-09",
    "price": 490300
  },
  {
    "date": "2016-10",
    "price": 492000
  },
  {
    "date": "2016-11",
    "price": 494200
  },
  {
    "date": "2016-12",
    "price": 496900
  },
  {
    "date": "2017-01",
    "price": 498700
  },
  {
    "date": "2017-02",
    "price": 499800
  },
  {
    "date": "2017-03",
    "price": 503100
  },
  {
    "date": "2017-04",
    "price": 502500
  },
  {
    "date": "2017-05",
    "price": 496300
  },
  {
    "date": "2017-06",
    "price": 488100
  },
  {
    "date": "2017-07",
    "price": 485700
  },
  {
    "date": "2017-08",
    "price": 487500
  },
  {
    "date": "2017-09",
    "price": 490300
  },
  {
    "date": "2017-10",
    "price": 493700
  },
  {
    "date": "2017-11",
    "price": 498000
  },
  {
    "date": "2017-12",
    "price": 501100
  },
  {
    "date": "2018-01",
    "price": 503400
  },
  {
    "date": "2018-02",
    "price": 505500
  },
  {
    "date": "2018-03",
    "price": 504600
  },
  {
    "date": "2018-04",
    "price": 506400
  },
  {
    "date": "2018-05",
    "price": 509200
  },
  {
    "date": "2018-06",
    "price": 508100
  },
  {
    "date": "2018-07",
    "price": 501900
  },
  {
    "date": "2018-08",
    "price": 497500
  },
  {
    "date": "2018-09",
    "price": 496100
  },
  {
    "date": "2018-10",
    "price": 496700
  },
  {
    "date": "2018-11",
    "price": 498300
  },
  {
    "date": "2018-12",
    "price": 501200
  },
  {
    "date": "2019-01",
    "price": 502900
  },
  {
    "date": "2019-02",
    "price": 503200
  },
  {
    "date": "2019-03",
    "price": 505300
  },
  {
    "date": "2019-04",
    "price": 508000
  }
]