[
  {
    "date": "1996-04",
    "price": 144600
  },
  {
    "date": "1996-05",
    "price": 144400
  },
  {
    "date": "1996-06",
    "price": 144400
  },
  {
    "date": "1996-07",
    "price": 144600
  },
  {
    "date": "1996-08",
    "price": 145000
  },
  {
    "date": "1996-09",
    "price": 145600
  },
  {
    "date": "1996-10",
    "price": 146200
  },
  {
    "date": "1996-11",
    "price": 146900
  },
  {
    "date": "1996-12",
    "price": 147500
  },
  {
    "date": "1997-01",
    "price": 148200
  },
  {
    "date": "1997-02",
    "price": 149100
  },
  {
    "date": "1997-03",
    "price": 150000
  },
  {
    "date": "1997-04",
    "price": 151100
  },
  {
    "date": "1997-05",
    "price": 152300
  },
  {
    "date": "1997-06",
    "price": 153500
  },
  {
    "date": "1997-07",
    "price": 154800
  },
  {
    "date": "1997-08",
    "price": 155900
  },
  {
    "date": "1997-09",
    "price": 156800
  },
  {
    "date": "1997-10",
    "price": 157500
  },
  {
    "date": "1997-11",
    "price": 158100
  },
  {
    "date": "1997-12",
    "price": 158400
  },
  {
    "date": "1998-01",
    "price": 158600
  },
  {
    "date": "1998-02",
    "price": 158700
  },
  {
    "date": "1998-03",
    "price": 158700
  },
  {
    "date": "1998-04",
    "price": 158400
  },
  {
    "date": "1998-05",
    "price": 158000
  },
  {
    "date": "1998-06",
    "price": 157600
  },
  {
    "date": "1998-07",
    "price": 157100
  },
  {
    "date": "1998-08",
    "price": 156700
  },
  {
    "date": "1998-09",
    "price": 156400
  },
  {
    "date": "1998-10",
    "price": 156200
  },
  {
    "date": "1998-11",
    "price": 156300
  },
  {
    "date": "1998-12",
    "price": 156400
  },
  {
    "date": "1999-01",
    "price": 156800
  },
  {
    "date": "1999-02",
    "price": 157500
  },
  {
    "date": "1999-03",
    "price": 158500
  },
  {
    "date": "1999-04",
    "price": 159700
  },
  {
    "date": "1999-05",
    "price": 161000
  },
  {
    "date": "1999-06",
    "price": 162300
  },
  {
    "date": "1999-07",
    "price": 163700
  },
  {
    "date": "1999-08",
    "price": 165100
  },
  {
    "date": "1999-09",
    "price": 166300
  },
  {
    "date": "1999-10",
    "price": 167500
  },
  {
    "date": "1999-11",
    "price": 168500
  },
  {
    "date": "1999-12",
    "price": 169500
  },
  {
    "date": "2000-01",
    "price": 170300
  },
  {
    "date": "2000-02",
    "price": 171000
  },
  {
    "date": "2000-03",
    "price": 171600
  },
  {
    "date": "2000-04",
    "price": 172000
  },
  {
    "date": "2000-05",
    "price": 172100
  },
  {
    "date": "2000-06",
    "price": 172200
  },
  {
    "date": "2000-07",
    "price": 172300
  },
  {
    "date": "2000-08",
    "price": 172500
  },
  {
    "date": "2000-09",
    "price": 172900
  },
  {
    "date": "2000-10",
    "price": 173700
  },
  {
    "date": "2000-11",
    "price": 174800
  },
  {
    "date": "2000-12",
    "price": 176200
  },
  {
    "date": "2001-01",
    "price": 177900
  },
  {
    "date": "2001-02",
    "price": 179800
  },
  {
    "date": "2001-03",
    "price": 181700
  },
  {
    "date": "2001-04",
    "price": 183400
  },
  {
    "date": "2001-05",
    "price": 184800
  },
  {
    "date": "2001-06",
    "price": 185900
  },
  {
    "date": "2001-07",
    "price": 186600
  },
  {
    "date": "2001-08",
    "price": 187100
  },
  {
    "date": "2001-09",
    "price": 187400
  },
  {
    "date": "2001-10",
    "price": 187700
  },
  {
    "date": "2001-11",
    "price": 187900
  },
  {
    "date": "2001-12",
    "price": 188200
  },
  {
    "date": "2002-01",
    "price": 188700
  },
  {
    "date": "2002-02",
    "price": 189500
  },
  {
    "date": "2002-03",
    "price": 190300
  },
  {
    "date": "2002-04",
    "price": 191200
  },
  {
    "date": "2002-05",
    "price": 192200
  },
  {
    "date": "2002-06",
    "price": 193200
  },
  {
    "date": "2002-07",
    "price": 194300
  },
  {
    "date": "2002-08",
    "price": 195500
  },
  {
    "date": "2002-09",
    "price": 196900
  },
  {
    "date": "2002-10",
    "price": 198300
  },
  {
    "date": "2002-11",
    "price": 200300
  },
  {
    "date": "2002-12",
    "price": 202500
  },
  {
    "date": "2003-01",
    "price": 204100
  },
  {
    "date": "2003-02",
    "price": 205100
  },
  {
    "date": "2003-03",
    "price": 206200
  },
  {
    "date": "2003-04",
    "price": 207800
  },
  {
    "date": "2003-05",
    "price": 210000
  },
  {
    "date": "2003-06",
    "price": 212800
  },
  {
    "date": "2003-07",
    "price": 216000
  },
  {
    "date": "2003-08",
    "price": 218900
  },
  {
    "date": "2003-09",
    "price": 221500
  },
  {
    "date": "2003-10",
    "price": 223800
  },
  {
    "date": "2003-11",
    "price": 225800
  },
  {
    "date": "2003-12",
    "price": 227700
  },
  {
    "date": "2004-01",
    "price": 229400
  },
  {
    "date": "2004-02",
    "price": 231200
  },
  {
    "date": "2004-03",
    "price": 233000
  },
  {
    "date": "2004-04",
    "price": 234700
  },
  {
    "date": "2004-05",
    "price": 236400
  },
  {
    "date": "2004-06",
    "price": 238300
  },
  {
    "date": "2004-07",
    "price": 240300
  },
  {
    "date": "2004-08",
    "price": 242600
  },
  {
    "date": "2004-09",
    "price": 245200
  },
  {
    "date": "2004-10",
    "price": 248200
  },
  {
    "date": "2004-11",
    "price": 251200
  },
  {
    "date": "2004-12",
    "price": 254400
  },
  {
    "date": "2005-01",
    "price": 257700
  },
  {
    "date": "2005-02",
    "price": 261000
  },
  {
    "date": "2005-03",
    "price": 264200
  },
  {
    "date": "2005-04",
    "price": 267500
  },
  {
    "date": "2005-05",
    "price": 270600
  },
  {
    "date": "2005-06",
    "price": 273600
  },
  {
    "date": "2005-07",
    "price": 276800
  },
  {
    "date": "2005-08",
    "price": 280100
  },
  {
    "date": "2005-09",
    "price": 283500
  },
  {
    "date": "2005-10",
    "price": 286900
  },
  {
    "date": "2005-11",
    "price": 290000
  },
  {
    "date": "2005-12",
    "price": 292700
  },
  {
    "date": "2006-01",
    "price": 295400
  },
  {
    "date": "2006-02",
    "price": 298400
  },
  {
    "date": "2006-03",
    "price": 301600
  },
  {
    "date": "2006-04",
    "price": 304700
  },
  {
    "date": "2006-05",
    "price": 307300
  },
  {
    "date": "2006-06",
    "price": 309100
  },
  {
    "date": "2006-07",
    "price": 310100
  },
  {
    "date": "2006-08",
    "price": 310700
  },
  {
    "date": "2006-09",
    "price": 311100
  },
  {
    "date": "2006-10",
    "price": 311300
  },
  {
    "date": "2006-11",
    "price": 311400
  },
  {
    "date": "2006-12",
    "price": 311500
  },
  {
    "date": "2007-01",
    "price": 311700
  },
  {
    "date": "2007-02",
    "price": 311700
  },
  {
    "date": "2007-03",
    "price": 311400
  },
  {
    "date": "2007-04",
    "price": 310900
  },
  {
    "date": "2007-05",
    "price": 310400
  },
  {
    "date": "2007-06",
    "price": 310100
  },
  {
    "date": "2007-07",
    "price": 310100
  },
  {
    "date": "2007-08",
    "price": 310000
  },
  {
    "date": "2007-09",
    "price": 309600
  },
  {
    "date": "2007-10",
    "price": 308800
  },
  {
    "date": "2007-11",
    "price": 307600
  },
  {
    "date": "2007-12",
    "price": 306100
  },
  {
    "date": "2008-01",
    "price": 304400
  },
  {
    "date": "2008-02",
    "price": 302600
  },
  {
    "date": "2008-03",
    "price": 301000
  },
  {
    "date": "2008-04",
    "price": 299300
  },
  {
    "date": "2008-05",
    "price": 297800
  },
  {
    "date": "2008-06",
    "price": 296400
  },
  {
    "date": "2008-07",
    "price": 294700
  },
  {
    "date": "2008-08",
    "price": 292600
  },
  {
    "date": "2008-09",
    "price": 290500
  },
  {
    "date": "2008-10",
    "price": 288400
  },
  {
    "date": "2008-11",
    "price": 286600
  },
  {
    "date": "2008-12",
    "price": 285200
  },
  {
    "date": "2009-01",
    "price": 284000
  },
  {
    "date": "2009-02",
    "price": 282800
  },
  {
    "date": "2009-03",
    "price": 281300
  },
  {
    "date": "2009-04",
    "price": 279600
  },
  {
    "date": "2009-05",
    "price": 277800
  },
  {
    "date": "2009-06",
    "price": 275900
  },
  {
    "date": "2009-07",
    "price": 274100
  },
  {
    "date": "2009-08",
    "price": 272500
  },
  {
    "date": "2009-09",
    "price": 270800
  },
  {
    "date": "2009-10",
    "price": 269300
  },
  {
    "date": "2009-11",
    "price": 268400
  },
  {
    "date": "2009-12",
    "price": 267800
  },
  {
    "date": "2010-01",
    "price": 267700
  },
  {
    "date": "2010-02",
    "price": 268200
  },
  {
    "date": "2010-03",
    "price": 269100
  },
  {
    "date": "2010-04",
    "price": 269700
  },
  {
    "date": "2010-05",
    "price": 269800
  },
  {
    "date": "2010-06",
    "price": 269000
  },
  {
    "date": "2010-07",
    "price": 267300
  },
  {
    "date": "2010-08",
    "price": 265800
  },
  {
    "date": "2010-09",
    "price": 265300
  },
  {
    "date": "2010-10",
    "price": 265800
  },
  {
    "date": "2010-11",
    "price": 266300
  },
  {
    "date": "2010-12",
    "price": 265900
  },
  {
    "date": "2011-01",
    "price": 264800
  },
  {
    "date": "2011-02",
    "price": 264100
  },
  {
    "date": "2011-03",
    "price": 263800
  },
  {
    "date": "2011-04",
    "price": 263700
  },
  {
    "date": "2011-05",
    "price": 263400
  },
  {
    "date": "2011-06",
    "price": 263600
  },
  {
    "date": "2011-07",
    "price": 264600
  },
  {
    "date": "2011-08",
    "price": 265700
  },
  {
    "date": "2011-09",
    "price": 265100
  },
  {
    "date": "2011-10",
    "price": 263900
  },
  {
    "date": "2011-11",
    "price": 262700
  },
  {
    "date": "2011-12",
    "price": 261500
  },
  {
    "date": "2012-01",
    "price": 259700
  },
  {
    "date": "2012-02",
    "price": 258000
  },
  {
    "date": "2012-03",
    "price": 257000
  },
  {
    "date": "2012-04",
    "price": 255000
  },
  {
    "date": "2012-05",
    "price": 252300
  },
  {
    "date": "2012-06",
    "price": 250600
  },
  {
    "date": "2012-07",
    "price": 250600
  },
  {
    "date": "2012-08",
    "price": 250800
  },
  {
    "date": "2012-09",
    "price": 252900
  },
  {
    "date": "2012-10",
    "price": 255600
  },
  {
    "date": "2012-11",
    "price": 256500
  },
  {
    "date": "2012-12",
    "price": 256400
  },
  {
    "date": "2013-01",
    "price": 257900
  },
  {
    "date": "2013-02",
    "price": 259700
  },
  {
    "date": "2013-03",
    "price": 261200
  },
  {
    "date": "2013-04",
    "price": 263600
  },
  {
    "date": "2013-05",
    "price": 267100
  },
  {
    "date": "2013-06",
    "price": 269700
  },
  {
    "date": "2013-07",
    "price": 270700
  },
  {
    "date": "2013-08",
    "price": 271500
  },
  {
    "date": "2013-09",
    "price": 271800
  },
  {
    "date": "2013-10",
    "price": 271200
  },
  {
    "date": "2013-11",
    "price": 271200
  },
  {
    "date": "2013-12",
    "price": 272100
  },
  {
    "date": "2014-01",
    "price": 273000
  },
  {
    "date": "2014-02",
    "price": 272200
  },
  {
    "date": "2014-03",
    "price": 270200
  },
  {
    "date": "2014-04",
    "price": 269300
  },
  {
    "date": "2014-05",
    "price": 269900
  },
  {
    "date": "2014-06",
    "price": 270100
  },
  {
    "date": "2014-07",
    "price": 270300
  },
  {
    "date": "2014-08",
    "price": 269900
  },
  {
    "date": "2014-09",
    "price": 268600
  },
  {
    "date": "2014-10",
    "price": 267300
  },
  {
    "date": "2014-11",
    "price": 267600
  },
  {
    "date": "2014-12",
    "price": 268200
  },
  {
    "date": "2015-01",
    "price": 268300
  },
  {
    "date": "2015-02",
    "price": 268400
  },
  {
    "date": "2015-03",
    "price": 269000
  },
  {
    "date": "2015-04",
    "price": 269500
  },
  {
    "date": "2015-05",
    "price": 270000
  },
  {
    "date": "2015-06",
    "price": 270200
  },
  {
    "date": "2015-07",
    "price": 270100
  },
  {
    "date": "2015-08",
    "price": 270300
  },
  {
    "date": "2015-09",
    "price": 270800
  },
  {
    "date": "2015-10",
    "price": 271000
  },
  {
    "date": "2015-11",
    "price": 271800
  },
  {
    "date": "2015-12",
    "price": 273100
  },
  {
    "date": "2016-01",
    "price": 273800
  },
  {
    "date": "2016-02",
    "price": 274000
  },
  {
    "date": "2016-03",
    "price": 273900
  },
  {
    "date": "2016-04",
    "price": 273700
  },
  {
    "date": "2016-05",
    "price": 274300
  },
  {
    "date": "2016-06",
    "price": 276300
  },
  {
    "date": "2016-07",
    "price": 279200
  },
  {
    "date": "2016-08",
    "price": 282100
  },
  {
    "date": "2016-09",
    "price": 284500
  },
  {
    "date": "2016-10",
    "price": 285900
  },
  {
    "date": "2016-11",
    "price": 286500
  },
  {
    "date": "2016-12",
    "price": 288200
  },
  {
    "date": "2017-01",
    "price": 291000
  },
  {
    "date": "2017-02",
    "price": 294100
  },
  {
    "date": "2017-03",
    "price": 296000
  },
  {
    "date": "2017-04",
    "price": 296500
  },
  {
    "date": "2017-05",
    "price": 296900
  },
  {
    "date": "2017-06",
    "price": 297700
  },
  {
    "date": "2017-07",
    "price": 297300
  },
  {
    "date": "2017-08",
    "price": 296700
  },
  {
    "date": "2017-09",
    "price": 297500
  },
  {
    "date": "2017-10",
    "price": 298400
  },
  {
    "date": "2017-11",
    "price": 298400
  },
  {
    "date": "2017-12",
    "price": 297900
  },
  {
    "date": "2018-01",
    "price": 297000
  },
  {
    "date": "2018-02",
    "price": 296300
  },
  {
    "date": "2018-03",
    "price": 296700
  },
  {
    "date": "2018-04",
    "price": 298200
  },
  {
    "date": "2018-05",
    "price": 299300
  },
  {
    "date": "2018-06",
    "price": 300300
  },
  {
    "date": "2018-07",
    "price": 301800
  },
  {
    "date": "2018-08",
    "price": 303300
  },
  {
    "date": "2018-09",
    "price": 304300
  },
  {
    "date": "2018-10",
    "price": 305800
  },
  {
    "date": "2018-11",
    "price": 307400
  },
  {
    "date": "2018-12",
    "price": 308500
  },
  {
    "date": "2019-01",
    "price": 309900
  },
  {
    "date": "2019-02",
    "price": 311400
  },
  {
    "date": "2019-03",
    "price": 312900
  },
  {
    "date": "2019-04",
    "price": 313900
  }
]